data_catalog_doccano_api/__init__.py
data_catalog_doccano_api/doccano_api.py
data_catalog_doccano_api-0.0.1.dist-info/LICENSE
data_catalog_doccano_api-0.0.1.dist-info/METADATA
data_catalog_doccano_api-0.0.1.dist-info/WHEEL
data_catalog_doccano_api-0.0.1.dist-info/top_level.txt
data_catalog_doccano_api-0.0.1.dist-info/RECORD
