Metadata-Version: 2.1
Name: data-catalog-doccano-api
Version: 0.0.1
Summary: Wrapper for doccano api
Home-page: UNKNOWN
Author: NAV IKT
License: MIT
Project-URL: Bug Tracker, https://github.com/navikt/data-catalog-dcat-validator
Project-URL: Documentation, https://github.com/navikt/data-catalog-dcat-validator
Project-URL: Source Code, https://github.com/navikt/data-catalog-dcat-validator
Platform: UNKNOWN
Classifier: Development Status :: 3 - Alpha
Classifier: License :: OSI Approved :: MIT License
Classifier: Programming Language :: Python :: 3.6
Classifier: Programming Language :: Python :: 3.7
Requires-Python: >=3.6
Requires-Dist: requests (==2.22.0)
